{
  "item": [
    {
      "id": "6e99de83-2f6d-4cb2-a184-64f31ac5967f",
      "name": "Config",
      "description": {
        "content": "Manage remote configuration key-value pairs",
        "type": "text/plain"
      },
      "item": [
        {
          "id": "69d8d8c5-4bdf-47fa-bf34-1c141fdbea80",
          "name": "List Remote Configs",
          "request": {
            "name": "List Remote Configs",
            "description": {
              "content": "Returns all configuration schemas and their settings for the specified project environment.",
              "type": "text/plain"
            },
            "url": {
              "path": [
                "v1",
                "projects",
                ":projectId",
                "environments",
                ":environmentId",
                "configs"
              ],
              "host": [
                "{{baseUrl}}"
              ],
              "query": [],
              "variable": [
                {
                  "disabled": false,
                  "type": "any",
                  "value": "<string>",
                  "key": "projectId",
                  "description": "(Required) "
                },
                {
                  "disabled": false,
                  "type": "any",
                  "value": "<string>",
                  "key": "environmentId",
                  "description": "(Required) "
                }
              ]
            },
            "header": [
              {
                "key": "Accept",
                "value": "application/json"
              }
            ],
            "method": "GET",
            "auth": null
          },
          "response": [
            {
              "id": "26378373-dfbc-4f56-98f4-b312b64ccff7",
              "name": "List of configurations",
              "originalRequest": {
                "url": {
                  "path": [
                    "v1",
                    "projects",
                    ":projectId",
                    "environments",
                    ":environmentId",
                    "configs"
                  ],
                  "host": [
                    "{{baseUrl}}"
                  ],
                  "query": [],
                  "variable": [
                    {
                      "disabled": false,
                      "type": "any",
                      "value": "<string>",
                      "key": "projectId",
                      "description": "(Required) "
                    },
                    {
                      "disabled": false,
                      "type": "any",
                      "value": "<string>",
                      "key": "environmentId",
                      "description": "(Required) "
                    }
                  ]
                },
                "header": [
                  {
                    "description": {
                      "content": "Added as a part of security scheme: bearer",
                      "type": "text/plain"
                    },
                    "key": "Authorization",
                    "value": "Bearer <token>"
                  },
                  {
                    "key": "Accept",
                    "value": "application/json"
                  }
                ],
                "method": "GET",
                "body": {}
              },
              "status": "OK",
              "code": 200,
              "header": [
                {
                  "key": "Content-Type",
                  "value": "application/json"
                }
              ],
              "body": "{\n  \"configs\": [\n    {\n      \"id\": \"string\",\n      \"type\": \"settings\",\n      \"projectId\": \"string\",\n      \"environmentId\": \"string\",\n      \"createdAt\": \"2013-04-28T21:36:45.780Z\",\n      \"updatedAt\": \"1950-05-04T08:13:01.179Z\",\n      \"value\": [\n        {\n          \"key\": \"<string>\",\n          \"type\": \"<string>\",\n          \"value\": \"\",\n          \"description\": \"<string>\"\n        },\n        {\n          \"key\": \"<string>\",\n          \"type\": \"<string>\",\n          \"value\": \"\",\n          \"description\": \"<string>\"\n        }\n      ]\n    },\n    {\n      \"id\": \"string\",\n      \"type\": \"settings\",\n      \"projectId\": \"string\",\n      \"environmentId\": \"string\",\n      \"createdAt\": \"2015-06-05T05:46:57.725Z\",\n      \"updatedAt\": \"1949-06-20T07:43:26.094Z\",\n      \"value\": [\n        {\n          \"key\": \"<string>\",\n          \"type\": \"<string>\",\n          \"value\": \"\",\n          \"description\": \"<string>\"\n        },\n        {\n          \"key\": \"<string>\",\n          \"type\": \"<string>\",\n          \"value\": \"\",\n          \"description\": \"<string>\"\n        }\n      ]\n    }\n  ]\n}",
              "cookie": [],
              "_postman_previewlanguage": "json"
            },
            {
              "id": "4ab35cce-1896-495c-9399-b303da117a50",
              "name": "Unauthorized",
              "originalRequest": {
                "url": {
                  "path": [
                    "v1",
                    "projects",
                    ":projectId",
                    "environments",
                    ":environmentId",
                    "configs"
                  ],
                  "host": [
                    "{{baseUrl}}"
                  ],
                  "query": [],
                  "variable": [
                    {
                      "disabled": false,
                      "type": "any",
                      "value": "<string>",
                      "key": "projectId",
                      "description": "(Required) "
                    },
                    {
                      "disabled": false,
                      "type": "any",
                      "value": "<string>",
                      "key": "environmentId",
                      "description": "(Required) "
                    }
                  ]
                },
                "header": [
                  {
                    "description": {
                      "content": "Added as a part of security scheme: bearer",
                      "type": "text/plain"
                    },
                    "key": "Authorization",
                    "value": "Bearer <token>"
                  }
                ],
                "method": "GET",
                "body": {}
              },
              "status": "Unauthorized",
              "code": 401,
              "header": [
                {
                  "key": "Content-Type",
                  "value": "text/plain"
                }
              ],
              "body": "",
              "cookie": [],
              "_postman_previewlanguage": "text"
            }
          ],
          "event": [],
          "protocolProfileBehavior": {
            "disableBodyPruning": true
          }
        },
        {
          "id": "5b1dcc79-be3d-4857-b6bc-86cd97901a03",
          "name": "Get Remote Config",
          "request": {
            "name": "Get Remote Config",
            "description": {
              "content": "Returns a specific configuration with all its settings.",
              "type": "text/plain"
            },
            "url": {
              "path": [
                "v1",
                "projects",
                ":projectId",
                "environments",
                ":environmentId",
                "configs",
                ":configId"
              ],
              "host": [
                "{{baseUrl}}"
              ],
              "query": [],
              "variable": [
                {
                  "disabled": false,
                  "type": "any",
                  "value": "<string>",
                  "key": "projectId",
                  "description": "(Required) "
                },
                {
                  "disabled": false,
                  "type": "any",
                  "value": "<string>",
                  "key": "environmentId",
                  "description": "(Required) "
                },
                {
                  "disabled": false,
                  "type": "any",
                  "value": "<string>",
                  "key": "configId",
                  "description": "(Required) "
                }
              ]
            },
            "header": [
              {
                "key": "Accept",
                "value": "application/json"
              }
            ],
            "method": "GET",
            "auth": null
          },
          "response": [
            {
              "id": "951d73b4-6844-4bda-ae6c-480fd1f922b5",
              "name": "Configuration details",
              "originalRequest": {
                "url": {
                  "path": [
                    "v1",
                    "projects",
                    ":projectId",
                    "environments",
                    ":environmentId",
                    "configs",
                    ":configId"
                  ],
                  "host": [
                    "{{baseUrl}}"
                  ],
                  "query": [],
                  "variable": [
                    {
                      "disabled": false,
                      "type": "any",
                      "value": "<string>",
                      "key": "projectId",
                      "description": "(Required) "
                    },
                    {
                      "disabled": false,
                      "type": "any",
                      "value": "<string>",
                      "key": "environmentId",
                      "description": "(Required) "
                    },
                    {
                      "disabled": false,
                      "type": "any",
                      "value": "<string>",
                      "key": "configId",
                      "description": "(Required) "
                    }
                  ]
                },
                "header": [
                  {
                    "description": {
                      "content": "Added as a part of security scheme: bearer",
                      "type": "text/plain"
                    },
                    "key": "Authorization",
                    "value": "Bearer <token>"
                  },
                  {
                    "key": "Accept",
                    "value": "application/json"
                  }
                ],
                "method": "GET",
                "body": {}
              },
              "status": "OK",
              "code": 200,
              "header": [
                {
                  "key": "Content-Type",
                  "value": "application/json"
                }
              ],
              "body": "{\n  \"id\": \"string\",\n  \"type\": \"settings\",\n  \"projectId\": \"string\",\n  \"environmentId\": \"string\",\n  \"createdAt\": \"1990-11-03T23:57:39.162Z\",\n  \"updatedAt\": \"1998-08-09T00:37:08.278Z\",\n  \"value\": [\n    {\n      \"key\": \"<string>\",\n      \"type\": \"<string>\",\n      \"value\": \"\",\n      \"description\": \"<string>\"\n    },\n    {\n      \"key\": \"<string>\",\n      \"type\": \"<string>\",\n      \"value\": \"\",\n      \"description\": \"<string>\"\n    }\n  ]\n}",
              "cookie": [],
              "_postman_previewlanguage": "json"
            },
            {
              "id": "1d7317cd-003a-43fe-8274-71017bbe4889",
              "name": "Config not found",
              "originalRequest": {
                "url": {
                  "path": [
                    "v1",
                    "projects",
                    ":projectId",
                    "environments",
                    ":environmentId",
                    "configs",
                    ":configId"
                  ],
                  "host": [
                    "{{baseUrl}}"
                  ],
                  "query": [],
                  "variable": [
                    {
                      "disabled": false,
                      "type": "any",
                      "value": "<string>",
                      "key": "projectId",
                      "description": "(Required) "
                    },
                    {
                      "disabled": false,
                      "type": "any",
                      "value": "<string>",
                      "key": "environmentId",
                      "description": "(Required) "
                    },
                    {
                      "disabled": false,
                      "type": "any",
                      "value": "<string>",
                      "key": "configId",
                      "description": "(Required) "
                    }
                  ]
                },
                "header": [
                  {
                    "description": {
                      "content": "Added as a part of security scheme: bearer",
                      "type": "text/plain"
                    },
                    "key": "Authorization",
                    "value": "Bearer <token>"
                  }
                ],
                "method": "GET",
                "body": {}
              },
              "status": "Not Found",
              "code": 404,
              "header": [
                {
                  "key": "Content-Type",
                  "value": "text/plain"
                }
              ],
              "body": "",
              "cookie": [],
              "_postman_previewlanguage": "text"
            }
          ],
          "event": [],
          "protocolProfileBehavior": {
            "disableBodyPruning": true
          }
        },
        {
          "id": "13340e90-d7f0-44c7-8201-b6c223e1b47b",
          "name": "Update Remote Config",
          "request": {
            "name": "Update Remote Config",
            "description": {
              "content": "Creates or updates the complete set of settings for a configuration.",
              "type": "text/plain"
            },
            "url": {
              "path": [
                "v1",
                "projects",
                ":projectId",
                "environments",
                ":environmentId",
                "configs",
                ":configId"
              ],
              "host": [
                "{{baseUrl}}"
              ],
              "query": [],
              "variable": [
                {
                  "disabled": false,
                  "type": "any",
                  "value": "<string>",
                  "key": "projectId",
                  "description": "(Required) "
                },
                {
                  "disabled": false,
                  "type": "any",
                  "value": "<string>",
                  "key": "environmentId",
                  "description": "(Required) "
                },
                {
                  "disabled": false,
                  "type": "any",
                  "value": "<string>",
                  "key": "configId",
                  "description": "(Required) "
                }
              ]
            },
            "header": [
              {
                "key": "Content-Type",
                "value": "application/json"
              },
              {
                "key": "Accept",
                "value": "application/json"
              }
            ],
            "method": "PUT",
            "auth": null,
            "body": {
              "mode": "raw",
              "raw": "{\n  \"type\": \"<string>\",\n  \"value\": [\n    {\n      \"key\": \"<string>\",\n      \"type\": \"<string>\",\n      \"value\": \"\",\n      \"description\": \"<string>\"\n    },\n    {\n      \"key\": \"<string>\",\n      \"type\": \"<string>\",\n      \"value\": \"\",\n      \"description\": \"<string>\"\n    }\n  ]\n}",
              "options": {
                "raw": {
                  "language": "json"
                }
              }
            }
          },
          "response": [
            {
              "id": "c21e357e-bd69-41bc-b2b6-eca89305276e",
              "name": "Configuration updated",
              "originalRequest": {
                "url": {
                  "path": [
                    "v1",
                    "projects",
                    ":projectId",
                    "environments",
                    ":environmentId",
                    "configs",
                    ":configId"
                  ],
                  "host": [
                    "{{baseUrl}}"
                  ],
                  "query": [],
                  "variable": [
                    {
                      "disabled": false,
                      "type": "any",
                      "value": "<string>",
                      "key": "projectId",
                      "description": "(Required) "
                    },
                    {
                      "disabled": false,
                      "type": "any",
                      "value": "<string>",
                      "key": "environmentId",
                      "description": "(Required) "
                    },
                    {
                      "disabled": false,
                      "type": "any",
                      "value": "<string>",
                      "key": "configId",
                      "description": "(Required) "
                    }
                  ]
                },
                "header": [
                  {
                    "description": {
                      "content": "Added as a part of security scheme: bearer",
                      "type": "text/plain"
                    },
                    "key": "Authorization",
                    "value": "Bearer <token>"
                  },
                  {
                    "key": "Accept",
                    "value": "application/json"
                  }
                ],
                "method": "PUT",
                "body": {
                  "mode": "raw",
                  "raw": "{\n  \"type\": \"<string>\",\n  \"value\": [\n    {\n      \"key\": \"<string>\",\n      \"type\": \"<string>\",\n      \"value\": \"\",\n      \"description\": \"<string>\"\n    },\n    {\n      \"key\": \"<string>\",\n      \"type\": \"<string>\",\n      \"value\": \"\",\n      \"description\": \"<string>\"\n    }\n  ]\n}",
                  "options": {
                    "raw": {
                      "language": "json"
                    }
                  }
                }
              },
              "status": "OK",
              "code": 200,
              "header": [
                {
                  "key": "Content-Type",
                  "value": "application/json"
                }
              ],
              "body": "{\n  \"id\": \"string\",\n  \"type\": \"settings\",\n  \"projectId\": \"string\",\n  \"environmentId\": \"string\",\n  \"createdAt\": \"1990-11-03T23:57:39.162Z\",\n  \"updatedAt\": \"1998-08-09T00:37:08.278Z\",\n  \"value\": [\n    {\n      \"key\": \"<string>\",\n      \"type\": \"<string>\",\n      \"value\": \"\",\n      \"description\": \"<string>\"\n    },\n    {\n      \"key\": \"<string>\",\n      \"type\": \"<string>\",\n      \"value\": \"\",\n      \"description\": \"<string>\"\n    }\n  ]\n}",
              "cookie": [],
              "_postman_previewlanguage": "json"
            }
          ],
          "event": [],
          "protocolProfileBehavior": {
            "disableBodyPruning": true
          }
        }
      ],
      "event": []
    },
    {
      "id": "f2d57090-494a-4e14-a8e5-e7295d2298db",
      "name": "Settings",
      "description": {
        "content": "Manage configuration settings and schemas",
        "type": "text/plain"
      },
      "item": [
        {
          "id": "754fa376-4bae-45b7-b262-2cfe7b55ab44",
          "name": "List Config Settings",
          "request": {
            "name": "List Config Settings",
            "description": {
              "content": "Returns all settings (key-value pairs) in the configuration.",
              "type": "text/plain"
            },
            "url": {
              "path": [
                "v1",
                "projects",
                ":projectId",
                "environments",
                ":environmentId",
                "configs",
                ":configId",
                "settings"
              ],
              "host": [
                "{{baseUrl}}"
              ],
              "query": [],
              "variable": [
                {
                  "disabled": false,
                  "type": "any",
                  "value": "<string>",
                  "key": "projectId",
                  "description": "(Required) "
                },
                {
                  "disabled": false,
                  "type": "any",
                  "value": "<string>",
                  "key": "environmentId",
                  "description": "(Required) "
                },
                {
                  "disabled": false,
                  "type": "any",
                  "value": "<string>",
                  "key": "configId",
                  "description": "(Required) "
                }
              ]
            },
            "header": [
              {
                "key": "Accept",
                "value": "application/json"
              }
            ],
            "method": "GET",
            "auth": null
          },
          "response": [
            {
              "id": "157562e6-5289-4b06-aea9-c1a5ba675bb1",
              "name": "Configuration settings",
              "originalRequest": {
                "url": {
                  "path": [
                    "v1",
                    "projects",
                    ":projectId",
                    "environments",
                    ":environmentId",
                    "configs",
                    ":configId",
                    "settings"
                  ],
                  "host": [
                    "{{baseUrl}}"
                  ],
                  "query": [],
                  "variable": [
                    {
                      "disabled": false,
                      "type": "any",
                      "value": "<string>",
                      "key": "projectId",
                      "description": "(Required) "
                    },
                    {
                      "disabled": false,
                      "type": "any",
                      "value": "<string>",
                      "key": "environmentId",
                      "description": "(Required) "
                    },
                    {
                      "disabled": false,
                      "type": "any",
                      "value": "<string>",
                      "key": "configId",
                      "description": "(Required) "
                    }
                  ]
                },
                "header": [
                  {
                    "description": {
                      "content": "Added as a part of security scheme: bearer",
                      "type": "text/plain"
                    },
                    "key": "Authorization",
                    "value": "Bearer <token>"
                  },
                  {
                    "key": "Accept",
                    "value": "application/json"
                  }
                ],
                "method": "GET",
                "body": {}
              },
              "status": "OK",
              "code": 200,
              "header": [
                {
                  "key": "Content-Type",
                  "value": "application/json"
                }
              ],
              "body": "{\n  \"items\": [\n    {\n      \"key\": \"<string>\",\n      \"type\": \"<string>\",\n      \"value\": \"\",\n      \"description\": \"<string>\"\n    },\n    {\n      \"key\": \"<string>\",\n      \"type\": \"<string>\",\n      \"value\": \"\",\n      \"description\": \"<string>\"\n    }\n  ]\n}",
              "cookie": [],
              "_postman_previewlanguage": "json"
            }
          ],
          "event": [],
          "protocolProfileBehavior": {
            "disableBodyPruning": true
          }
        },
        {
          "id": "6123bd93-139a-4a77-af48-5fb5a1348ab5",
          "name": "Add Config Setting",
          "request": {
            "name": "Add Config Setting",
            "description": {
              "content": "Adds a new key-value setting to the configuration.",
              "type": "text/plain"
            },
            "url": {
              "path": [
                "v1",
                "projects",
                ":projectId",
                "environments",
                ":environmentId",
                "configs",
                ":configId",
                "settings"
              ],
              "host": [
                "{{baseUrl}}"
              ],
              "query": [],
              "variable": [
                {
                  "disabled": false,
                  "type": "any",
                  "value": "<string>",
                  "key": "projectId",
                  "description": "(Required) "
                },
                {
                  "disabled": false,
                  "type": "any",
                  "value": "<string>",
                  "key": "environmentId",
                  "description": "(Required) "
                },
                {
                  "disabled": false,
                  "type": "any",
                  "value": "<string>",
                  "key": "configId",
                  "description": "(Required) "
                }
              ]
            },
            "header": [
              {
                "key": "Content-Type",
                "value": "application/json"
              },
              {
                "key": "Accept",
                "value": "application/json"
              }
            ],
            "method": "POST",
            "auth": null,
            "body": {
              "mode": "raw",
              "raw": "{\n  \"key\": \"<string>\",\n  \"type\": \"<string>\",\n  \"value\": \"\",\n  \"description\": \"<string>\"\n}",
              "options": {
                "raw": {
                  "language": "json"
                }
              }
            }
          },
          "response": [
            {
              "id": "65d7a5ca-293b-4fc6-8944-da47b79c89a0",
              "name": "Setting added",
              "originalRequest": {
                "url": {
                  "path": [
                    "v1",
                    "projects",
                    ":projectId",
                    "environments",
                    ":environmentId",
                    "configs",
                    ":configId",
                    "settings"
                  ],
                  "host": [
                    "{{baseUrl}}"
                  ],
                  "query": [],
                  "variable": [
                    {
                      "disabled": false,
                      "type": "any",
                      "value": "<string>",
                      "key": "projectId",
                      "description": "(Required) "
                    },
                    {
                      "disabled": false,
                      "type": "any",
                      "value": "<string>",
                      "key": "environmentId",
                      "description": "(Required) "
                    },
                    {
                      "disabled": false,
                      "type": "any",
                      "value": "<string>",
                      "key": "configId",
                      "description": "(Required) "
                    }
                  ]
                },
                "header": [
                  {
                    "description": {
                      "content": "Added as a part of security scheme: bearer",
                      "type": "text/plain"
                    },
                    "key": "Authorization",
                    "value": "Bearer <token>"
                  },
                  {
                    "key": "Accept",
                    "value": "application/json"
                  }
                ],
                "method": "POST",
                "body": {
                  "mode": "raw",
                  "raw": "{\n  \"key\": \"<string>\",\n  \"type\": \"<string>\",\n  \"value\": \"\",\n  \"description\": \"<string>\"\n}",
                  "options": {
                    "raw": {
                      "language": "json"
                    }
                  }
                }
              },
              "status": "OK",
              "code": 200,
              "header": [
                {
                  "key": "Content-Type",
                  "value": "application/json"
                }
              ],
              "body": "{\n  \"key\": \"<string>\",\n  \"type\": \"<string>\",\n  \"value\": \"\",\n  \"description\": \"<string>\"\n}",
              "cookie": [],
              "_postman_previewlanguage": "json"
            }
          ],
          "event": [],
          "protocolProfileBehavior": {
            "disableBodyPruning": true
          }
        }
      ],
      "event": []
    },
    {
      "id": "a9bec599-2dc0-4755-b129-8f36cf7fed98",
      "name": "Override Rules",
      "description": {
        "content": "Manage targeting rules for configuration overrides",
        "type": "text/plain"
      },
      "item": [
        {
          "id": "8ba116d6-274a-4152-84c8-8b08ece6bea5",
          "name": "List Override Rules",
          "request": {
            "name": "List Override Rules",
            "description": {
              "content": "Returns all override rules for the environment. Rules target specific player segments with configuration overrides.",
              "type": "text/plain"
            },
            "url": {
              "path": [
                "v1",
                "projects",
                ":projectId",
                "environments",
                ":environmentId",
                "rules"
              ],
              "host": [
                "{{baseUrl}}"
              ],
              "query": [],
              "variable": [
                {
                  "disabled": false,
                  "type": "any",
                  "value": "<string>",
                  "key": "projectId",
                  "description": "(Required) "
                },
                {
                  "disabled": false,
                  "type": "any",
                  "value": "<string>",
                  "key": "environmentId",
                  "description": "(Required) "
                }
              ]
            },
            "header": [
              {
                "key": "Accept",
                "value": "application/json"
              }
            ],
            "method": "GET",
            "auth": null
          },
          "response": [
            {
              "id": "c7badb8f-f667-4c8a-87e3-fe7d74c90a09",
              "name": "List of override rules",
              "originalRequest": {
                "url": {
                  "path": [
                    "v1",
                    "projects",
                    ":projectId",
                    "environments",
                    ":environmentId",
                    "rules"
                  ],
                  "host": [
                    "{{baseUrl}}"
                  ],
                  "query": [],
                  "variable": [
                    {
                      "disabled": false,
                      "type": "any",
                      "value": "<string>",
                      "key": "projectId",
                      "description": "(Required) "
                    },
                    {
                      "disabled": false,
                      "type": "any",
                      "value": "<string>",
                      "key": "environmentId",
                      "description": "(Required) "
                    }
                  ]
                },
                "header": [
                  {
                    "description": {
                      "content": "Added as a part of security scheme: bearer",
                      "type": "text/plain"
                    },
                    "key": "Authorization",
                    "value": "Bearer <token>"
                  },
                  {
                    "key": "Accept",
                    "value": "application/json"
                  }
                ],
                "method": "GET",
                "body": {}
              },
              "status": "OK",
              "code": 200,
              "header": [
                {
                  "key": "Content-Type",
                  "value": "application/json"
                }
              ],
              "body": "{\n  \"rules\": [\n    {\n      \"id\": \"string\",\n      \"name\": \"string\",\n      \"enabled\": true,\n      \"priority\": 5650,\n      \"condition\": \"string\",\n      \"rolloutPercentage\": 31,\n      \"startDate\": \"2014-08-05T00:16:23.324Z\",\n      \"endDate\": \"2011-01-12T04:42:57.739Z\",\n      \"value\": [\n        {\n          \"key\": \"string\",\n          \"type\": \"json\",\n          \"value\": \"\",\n          \"description\": \"string\"\n        },\n        {\n          \"key\": \"string\",\n          \"type\": \"json\",\n          \"value\": \"\",\n          \"description\": \"string\"\n        }\n      ]\n    },\n    {\n      \"id\": \"string\",\n      \"name\": \"string\",\n      \"enabled\": true,\n      \"priority\": 2468,\n      \"condition\": \"string\",\n      \"rolloutPercentage\": 4,\n      \"startDate\": \"1955-12-13T01:22:08.179Z\",\n      \"endDate\": \"2000-10-06T02:08:05.740Z\",\n      \"value\": [\n        {\n          \"key\": \"string\",\n          \"type\": \"string\",\n          \"value\": \"\",\n          \"description\": \"string\"\n        },\n        {\n          \"key\": \"string\",\n          \"type\": \"string\",\n          \"value\": \"\",\n          \"description\": \"string\"\n        }\n      ]\n    }\n  ]\n}",
              "cookie": [],
              "_postman_previewlanguage": "json"
            }
          ],
          "event": [],
          "protocolProfileBehavior": {
            "disableBodyPruning": true
          }
        },
        {
          "id": "03f223c0-b1a9-45d1-b7e2-8b549a2979c6",
          "name": "Create Override Rule",
          "request": {
            "name": "Create Override Rule",
            "description": {
              "content": "Creates a new override rule targeting a specific player segment with custom configuration values.",
              "type": "text/plain"
            },
            "url": {
              "path": [
                "v1",
                "projects",
                ":projectId",
                "environments",
                ":environmentId",
                "rules"
              ],
              "host": [
                "{{baseUrl}}"
              ],
              "query": [],
              "variable": [
                {
                  "disabled": false,
                  "type": "any",
                  "value": "<string>",
                  "key": "projectId",
                  "description": "(Required) "
                },
                {
                  "disabled": false,
                  "type": "any",
                  "value": "<string>",
                  "key": "environmentId",
                  "description": "(Required) "
                }
              ]
            },
            "header": [
              {
                "key": "Content-Type",
                "value": "application/json"
              },
              {
                "key": "Accept",
                "value": "application/json"
              }
            ],
            "method": "POST",
            "auth": null,
            "body": {
              "mode": "raw",
              "raw": "{\n  \"name\": \"<string>\",\n  \"enabled\": \"<boolean>\",\n  \"priority\": \"<integer>\",\n  \"condition\": \"<string>\",\n  \"value\": [\n    {\n      \"key\": \"<string>\",\n      \"type\": \"<string>\",\n      \"value\": \"\",\n      \"description\": \"<string>\"\n    },\n    {\n      \"key\": \"<string>\",\n      \"type\": \"<string>\",\n      \"value\": \"\",\n      \"description\": \"<string>\"\n    }\n  ],\n  \"rolloutPercentage\": 100,\n  \"startDate\": \"<dateTime>\",\n  \"endDate\": \"<dateTime>\"\n}",
              "options": {
                "raw": {
                  "language": "json"
                }
              }
            }
          },
          "response": [
            {
              "id": "d1b1d216-caa6-4af6-bfe9-2994a5d4937e",
              "name": "Rule created",
              "originalRequest": {
                "url": {
                  "path": [
                    "v1",
                    "projects",
                    ":projectId",
                    "environments",
                    ":environmentId",
                    "rules"
                  ],
                  "host": [
                    "{{baseUrl}}"
                  ],
                  "query": [],
                  "variable": [
                    {
                      "disabled": false,
                      "type": "any",
                      "value": "<string>",
                      "key": "projectId",
                      "description": "(Required) "
                    },
                    {
                      "disabled": false,
                      "type": "any",
                      "value": "<string>",
                      "key": "environmentId",
                      "description": "(Required) "
                    }
                  ]
                },
                "header": [
                  {
                    "description": {
                      "content": "Added as a part of security scheme: bearer",
                      "type": "text/plain"
                    },
                    "key": "Authorization",
                    "value": "Bearer <token>"
                  },
                  {
                    "key": "Accept",
                    "value": "application/json"
                  }
                ],
                "method": "POST",
                "body": {
                  "mode": "raw",
                  "raw": "{\n  \"name\": \"<string>\",\n  \"enabled\": \"<boolean>\",\n  \"priority\": \"<integer>\",\n  \"condition\": \"<string>\",\n  \"value\": [\n    {\n      \"key\": \"<string>\",\n      \"type\": \"<string>\",\n      \"value\": \"\",\n      \"description\": \"<string>\"\n    },\n    {\n      \"key\": \"<string>\",\n      \"type\": \"<string>\",\n      \"value\": \"\",\n      \"description\": \"<string>\"\n    }\n  ],\n  \"rolloutPercentage\": 100,\n  \"startDate\": \"<dateTime>\",\n  \"endDate\": \"<dateTime>\"\n}",
                  "options": {
                    "raw": {
                      "language": "json"
                    }
                  }
                }
              },
              "status": "OK",
              "code": 200,
              "header": [
                {
                  "key": "Content-Type",
                  "value": "application/json"
                }
              ],
              "body": "{\n  \"id\": \"string\",\n  \"name\": \"string\",\n  \"enabled\": false,\n  \"priority\": 5226,\n  \"condition\": \"string\",\n  \"rolloutPercentage\": 0,\n  \"startDate\": \"2002-03-30T10:28:27.856Z\",\n  \"endDate\": \"1950-05-10T09:50:46.859Z\",\n  \"value\": [\n    {\n      \"key\": \"<string>\",\n      \"type\": \"<string>\",\n      \"value\": \"\",\n      \"description\": \"<string>\"\n    },\n    {\n      \"key\": \"<string>\",\n      \"type\": \"<string>\",\n      \"value\": \"\",\n      \"description\": \"<string>\"\n    }\n  ]\n}",
              "cookie": [],
              "_postman_previewlanguage": "json"
            }
          ],
          "event": [],
          "protocolProfileBehavior": {
            "disableBodyPruning": true
          }
        },
        {
          "id": "5d0cd794-0c29-4f4f-9c8d-0c9e274723bf",
          "name": "Update Override Rule",
          "request": {
            "name": "Update Override Rule",
            "description": {
              "content": "Updates an existing override rule's conditions or settings.",
              "type": "text/plain"
            },
            "url": {
              "path": [
                "v1",
                "projects",
                ":projectId",
                "environments",
                ":environmentId",
                "rules",
                ":ruleId"
              ],
              "host": [
                "{{baseUrl}}"
              ],
              "query": [],
              "variable": [
                {
                  "disabled": false,
                  "type": "any",
                  "value": "<string>",
                  "key": "projectId",
                  "description": "(Required) "
                },
                {
                  "disabled": false,
                  "type": "any",
                  "value": "<string>",
                  "key": "environmentId",
                  "description": "(Required) "
                },
                {
                  "disabled": false,
                  "type": "any",
                  "value": "<string>",
                  "key": "ruleId",
                  "description": "(Required) "
                }
              ]
            },
            "header": [
              {
                "key": "Content-Type",
                "value": "application/json"
              },
              {
                "key": "Accept",
                "value": "application/json"
              }
            ],
            "method": "PUT",
            "auth": null,
            "body": {
              "mode": "raw",
              "raw": "{\n  \"name\": \"<string>\",\n  \"enabled\": \"<boolean>\",\n  \"priority\": \"<integer>\",\n  \"condition\": \"<string>\",\n  \"rolloutPercentage\": \"<integer>\",\n  \"startDate\": \"<dateTime>\",\n  \"endDate\": \"<dateTime>\",\n  \"value\": [\n    {\n      \"key\": \"<string>\",\n      \"type\": \"<string>\",\n      \"value\": \"\",\n      \"description\": \"<string>\"\n    },\n    {\n      \"key\": \"<string>\",\n      \"type\": \"<string>\",\n      \"value\": \"\",\n      \"description\": \"<string>\"\n    }\n  ]\n}",
              "options": {
                "raw": {
                  "language": "json"
                }
              }
            }
          },
          "response": [
            {
              "id": "8c540c5d-9ee8-4d94-a795-7fac162b3c43",
              "name": "Rule updated",
              "originalRequest": {
                "url": {
                  "path": [
                    "v1",
                    "projects",
                    ":projectId",
                    "environments",
                    ":environmentId",
                    "rules",
                    ":ruleId"
                  ],
                  "host": [
                    "{{baseUrl}}"
                  ],
                  "query": [],
                  "variable": [
                    {
                      "disabled": false,
                      "type": "any",
                      "value": "<string>",
                      "key": "projectId",
                      "description": "(Required) "
                    },
                    {
                      "disabled": false,
                      "type": "any",
                      "value": "<string>",
                      "key": "environmentId",
                      "description": "(Required) "
                    },
                    {
                      "disabled": false,
                      "type": "any",
                      "value": "<string>",
                      "key": "ruleId",
                      "description": "(Required) "
                    }
                  ]
                },
                "header": [
                  {
                    "description": {
                      "content": "Added as a part of security scheme: bearer",
                      "type": "text/plain"
                    },
                    "key": "Authorization",
                    "value": "Bearer <token>"
                  },
                  {
                    "key": "Accept",
                    "value": "application/json"
                  }
                ],
                "method": "PUT",
                "body": {
                  "mode": "raw",
                  "raw": "{\n  \"name\": \"<string>\",\n  \"enabled\": \"<boolean>\",\n  \"priority\": \"<integer>\",\n  \"condition\": \"<string>\",\n  \"rolloutPercentage\": \"<integer>\",\n  \"startDate\": \"<dateTime>\",\n  \"endDate\": \"<dateTime>\",\n  \"value\": [\n    {\n      \"key\": \"<string>\",\n      \"type\": \"<string>\",\n      \"value\": \"\",\n      \"description\": \"<string>\"\n    },\n    {\n      \"key\": \"<string>\",\n      \"type\": \"<string>\",\n      \"value\": \"\",\n      \"description\": \"<string>\"\n    }\n  ]\n}",
                  "options": {
                    "raw": {
                      "language": "json"
                    }
                  }
                }
              },
              "status": "OK",
              "code": 200,
              "header": [
                {
                  "key": "Content-Type",
                  "value": "application/json"
                }
              ],
              "body": "{\n  \"id\": \"string\",\n  \"name\": \"string\",\n  \"enabled\": false,\n  \"priority\": 5226,\n  \"condition\": \"string\",\n  \"rolloutPercentage\": 0,\n  \"startDate\": \"2002-03-30T10:28:27.856Z\",\n  \"endDate\": \"1950-05-10T09:50:46.859Z\",\n  \"value\": [\n    {\n      \"key\": \"<string>\",\n      \"type\": \"<string>\",\n      \"value\": \"\",\n      \"description\": \"<string>\"\n    },\n    {\n      \"key\": \"<string>\",\n      \"type\": \"<string>\",\n      \"value\": \"\",\n      \"description\": \"<string>\"\n    }\n  ]\n}",
              "cookie": [],
              "_postman_previewlanguage": "json"
            }
          ],
          "event": [],
          "protocolProfileBehavior": {
            "disableBodyPruning": true
          }
        },
        {
          "id": "20eaf1b8-a0e1-46f6-890f-f64f237a4d95",
          "name": "Delete Override Rule",
          "request": {
            "name": "Delete Override Rule",
            "description": {
              "content": "Deletes a targeting override rule.",
              "type": "text/plain"
            },
            "url": {
              "path": [
                "v1",
                "projects",
                ":projectId",
                "environments",
                ":environmentId",
                "rules",
                ":ruleId"
              ],
              "host": [
                "{{baseUrl}}"
              ],
              "query": [],
              "variable": [
                {
                  "disabled": false,
                  "type": "any",
                  "value": "<string>",
                  "key": "projectId",
                  "description": "(Required) "
                },
                {
                  "disabled": false,
                  "type": "any",
                  "value": "<string>",
                  "key": "environmentId",
                  "description": "(Required) "
                },
                {
                  "disabled": false,
                  "type": "any",
                  "value": "<string>",
                  "key": "ruleId",
                  "description": "(Required) "
                }
              ]
            },
            "method": "DELETE",
            "auth": null
          },
          "response": [
            {
              "id": "29fe3bc0-c3f9-4792-a455-66af17d4d58d",
              "name": "Rule deleted",
              "originalRequest": {
                "url": {
                  "path": [
                    "v1",
                    "projects",
                    ":projectId",
                    "environments",
                    ":environmentId",
                    "rules",
                    ":ruleId"
                  ],
                  "host": [
                    "{{baseUrl}}"
                  ],
                  "query": [],
                  "variable": [
                    {
                      "disabled": false,
                      "type": "any",
                      "value": "<string>",
                      "key": "projectId",
                      "description": "(Required) "
                    },
                    {
                      "disabled": false,
                      "type": "any",
                      "value": "<string>",
                      "key": "environmentId",
                      "description": "(Required) "
                    },
                    {
                      "disabled": false,
                      "type": "any",
                      "value": "<string>",
                      "key": "ruleId",
                      "description": "(Required) "
                    }
                  ]
                },
                "header": [
                  {
                    "description": {
                      "content": "Added as a part of security scheme: bearer",
                      "type": "text/plain"
                    },
                    "key": "Authorization",
                    "value": "Bearer <token>"
                  }
                ],
                "method": "DELETE",
                "body": {}
              },
              "status": "No Content",
              "code": 204,
              "header": [
                {
                  "key": "Content-Type",
                  "value": "text/plain"
                }
              ],
              "body": "",
              "cookie": [],
              "_postman_previewlanguage": "text"
            }
          ],
          "event": [],
          "protocolProfileBehavior": {
            "disableBodyPruning": true
          }
        }
      ],
      "event": []
    }
  ],
  "event": [],
  "variable": [
    {
      "type": "string",
      "value": "https://remote-config.services.api.unity.com",
      "key": "baseUrl"
    }
  ],
  "auth": {
    "type": "bearer",
    "bearer": [
      {
        "key": "token",
        "value": "{{bearerToken}}"
      }
    ]
  },
  "info": {
    "_postman_id": "eecd1bf0-a47a-44ba-890c-ab20fa5109e8",
    "name": "Unity Remote Config API",
    "schema": "https://schema.getpostman.com/json/collection/v2.1.0/collection.json",
    "description": {
      "content": "The Unity Remote Config REST API enables launching new features, testing functionality, and modifying game configurations without requiring app updates. The Admin API manages settings, schemas, and override rules. The Runtime API delivers configuration values to game clients at runtime.\n\nContact Support:\n Name: Unity Support",
      "type": "text/plain"
    }
  }
}